gridkit-1.0.1.dist-info/METADATA
gridkit-1.0.1.dist-info/WHEEL
gridkit/__init__.py
gridkit/_statistical_functions.py
gridkit/base_grid.py
gridkit/bounded_grid.py
gridkit/doc_utils.py
gridkit/errors.py
gridkit/gridkit_rs.cp310-win_amd64.pyd
gridkit/hex_grid.py
gridkit/index.py
gridkit/io.py
gridkit/rect_grid.py
gridkit/tile.py
gridkit/tri_grid.py
gridkit/version.py
gridkit-1.0.1.dist-info/RECORD
