Metadata-Version: 2.4
Name: gridkit
Version: 1.0.1
Classifier: Programming Language :: Rust
Classifier: Programming Language :: Python :: Implementation :: CPython
Classifier: Programming Language :: Python :: Implementation :: PyPy
Classifier: License :: OSI Approved :: MIT License
Requires-Dist: numpy
Requires-Dist: scipy
Requires-Dist: shapely
Requires-Dist: rasterio
Requires-Dist: pyproj
Requires-Dist: sphinx ; extra == 'doc'
Requires-Dist: sphinx-rtd-theme ; extra == 'doc'
Requires-Dist: sphinx-gallery ; extra == 'doc'
Requires-Dist: sphinxcontrib-plantuml ; extra == 'doc'
Requires-Dist: geopandas ; extra == 'doc'
Requires-Dist: dask[dataframe] ; extra == 'doc'
Requires-Dist: matplotlib ; extra == 'doc'
Requires-Dist: sphinx ; extra == 'test'
Requires-Dist: sphinx-rtd-theme ; extra == 'test'
Requires-Dist: sphinx-gallery ; extra == 'test'
Requires-Dist: sphinxcontrib-plantuml ; extra == 'test'
Requires-Dist: geopandas ; extra == 'test'
Requires-Dist: dask[dataframe] ; extra == 'test'
Requires-Dist: matplotlib ; extra == 'test'
Requires-Dist: black ; extra == 'test'
Requires-Dist: pytest ; extra == 'test'
Requires-Dist: pytest-cov ; extra == 'test'
Requires-Dist: pytest-pylint ; extra == 'test'
Requires-Dist: pytest-black ; extra == 'test'
Requires-Dist: pylint ; extra == 'test'
Requires-Dist: pre-commit ; extra == 'test'
Requires-Dist: maturin ; extra == 'test'
Provides-Extra: doc
Provides-Extra: test
Summary: Powerful abstractions of infinite grids for grid-vector interactions, tesselation, resampling and interactions between related grids.
Author-email: Timo Millenaar <tmillenaar@gmail.com>
Requires-Python: >=3.10
